mush/__init__.py
mush/api.py
mush/cli.py
mush/engine.py
mush/interfaces.py
mush/plugins/__init__.py
mush/plugins/access_secret_bash.py
mush/plugins/access_secret_python_keyring.py
mush/plugins/datastore_csv.py
mush/plugins/datastore_supernova.py
mush/plugins/persist_shell_bash.py
mush/plugins/persist_shell_gnome_terminal.py
mush/plugins/persist_shell_guake.py
mushtool-1.0.0.dist-info/DESCRIPTION.rst
mushtool-1.0.0.dist-info/METADATA
mushtool-1.0.0.dist-info/RECORD
mushtool-1.0.0.dist-info/WHEEL
mushtool-1.0.0.dist-info/entry_points.txt
mushtool-1.0.0.dist-info/metadata.json
mushtool-1.0.0.dist-info/top_level.txt
