Metadata-Version: 2.0
Name: mushtool
Version: 1.0.0
Summary: multi-use-shell-helper...tool...ok, it's a backronymn :)
Home-page: UNKNOWN
Author: UNKNOWN
Author-email: UNKNOWN
License: UNKNOWN
Platform: UNKNOWN
Requires-Dist: prettytable
